{
  "after": {
    "activePageText": "14",
    "has4000": true,
    "jumpInputValue": "14",
    "oneKeyCount": 60,
    "pagerText": "共 4000 条 1121314151667 前往页",
    "pagers": [
      {
        "active": "14",
        "i": 0,
        "input": "14",
        "text": "共 4000 条 1121314151667 前往页"
      }
    ],
    "risk": [],
    "skuCount": 60,
    "skus": [
      "10040370459975",
      "100099073137",
      "100239716149",
      "10163689342401",
      "12767632",
      "100019564964",
      "542634",
      "100003462913",
      "8023170",
      "10043931958262",
      "100114770505",
      "100024424532"
    ],
    "title": "京东联盟 - 网络赚钱，流量变现，专业电商CPS联盟平台！",
    "url": "https://union.jd.com/proManager/index?pageNo=14"
  },
  "after_all_product": {
    "activePageText": "13",
    "has4000": true,
    "jumpInputValue": "13",
    "oneKeyCount": 60,
    "pagerText": "共 4000 条 1111213141567 前往页",
    "pagers": [
      {
        "active": "13",
        "i": 0,
        "input": "13",
        "text": "共 4000 条 1111213141567 前往页"
      }
    ],
    "risk": [],
    "skuCount": 60,
    "skus": [
      "100012481790",
      "15257742",
      "10182281143663",
      "10084247457831",
      "100332454658",
      "100129686242",
      "100011855774",
      "10081835099648",
      "100157666071",
      "10116525834804",
      "100068407223",
      "100187688098"
    ],
    "title": "京东联盟 - 网络赚钱，流量变现，专业电商CPS联盟平台！",
    "url": "https://union.jd.com/proManager/index?pageNo=13"
  },
  "before": {
    "activePageText": "13",
    "has4000": true,
    "jumpInputValue": "13",
    "oneKeyCount": 60,
    "pagerText": "共 4000 条 1111213141567 前往页",
    "pagers": [
      {
        "active": "13",
        "i": 0,
        "input": "13",
        "text": "共 4000 条 1111213141567 前往页"
      }
    ],
    "risk": [],
    "skuCount": 60,
    "skus": [
      "100012481790",
      "15257742",
      "10182281143663",
      "10084247457831",
      "100332454658",
      "100129686242",
      "100011855774",
      "10081835099648",
      "100157666071",
      "10116525834804",
      "100068407223",
      "100187688098"
    ],
    "title": "京东联盟 - 网络赚钱，流量变现，专业电商CPS联盟平台！",
    "url": "https://union.jd.com/proManager/index?pageNo=13"
  },
  "jump_action": {
    "method": "4000_pager_locator_fill_enter",
    "ok": true
  },
  "ok": true,
  "reason": "safe_all_product_4000_page",
  "target_page": 14,
  "ts": "2026-06-15 11:18:58"
}